pypH/__init__.py
pypH/acid.py
pypH/species.py
pypH/spectator.py
pypH/system.py
pyph_toolkit-0.1.0.dist-info/licenses/LICENSE
pyph_toolkit-0.1.0.dist-info/METADATA
pyph_toolkit-0.1.0.dist-info/WHEEL
pyph_toolkit-0.1.0.dist-info/top_level.txt
pyph_toolkit-0.1.0.dist-info/RECORD
